[{"version":"1.0","dataId":4917429,"sourceId":104476,"sourceType":"TASK","sourceName":"SHJD-点云分割-20240418-(4)","validity":"UNKNOWN","classifications":[],"instances":[],"segments":[{"trackId":"6a496362-824c-4e7a-a1fd-e4c1ee7dacae","trackName":"1","contour":{"pointN":29917,"points":[]},"no":1,"deviceName":"lidar_point_cloud_0","deviceFrame":null,"bevFrameName":null,"id":"4de84641-5cc3-4908-a815-2d79a46ca4b4","type":"SEGMENTATION","classId":433092,"className":"green","classNumber":1,"classValues":[],"createdAt":1713497157000,"createdBy":10088},{"trackId":"2aaae89e-79e6-4efb-b34c-f51ea207f3ae","trackName":"2","contour":{"pointN":3634,"points":[]},"no":2,"deviceName":"lidar_point_cloud_0","deviceFrame":null,"bevFrameName":null,"id":"bce376b9-c65b-426c-8616-82ac2a83c7ca","type":"SEGMENTATION","classId":433091,"className":"red","classNumber":2,"classValues":[],"createdAt":1713497157000,"createdBy":10088},{"trackId":"9195fc5c-9bd0-4f2c-8fd6-691a2f43dcb7","trackName":"3","contour":{"pointN":4,"points":[]},"no":3,"deviceName":"lidar_point_cloud_0","deviceFrame":null,"bevFrameName":null,"id":"cff31185-8cae-4917-b73f-44093f275062","type":"SEGMENTATION","classId":433093,"className":"blue","classNumber":4,"classValues":[],"createdAt":1713497157000,"createdBy":10088},{"trackId":"4ab8d73f-24b3-4c81-8d6e-60e79f18b749","trackName":"4","contour":{"pointN":129,"points":[]},"no":4,"deviceName":"lidar_point_cloud_0","deviceFrame":null,"bevFrameName":null,"id":"ebc9c318-93df-400a-85c9-141a9ec6a623","type":"SEGMENTATION","classId":403778,"className":"pink","classNumber":3,"classValues":[],"createdAt":1715567463000,"createdBy":10524}],"entities":[],"relations":[]}]