[{"version":"1.0","dataId":4917610,"sourceId":104477,"sourceType":"TASK","sourceName":"SHJD-点云分割-20240418-(5)","validity":"UNKNOWN","classifications":[],"instances":[],"segments":[{"trackId":"19bf93eb-ecef-4409-8777-73c39a9a1585","trackName":"1","contour":{"pointN":28103,"points":[]},"no":1,"deviceName":"lidar_point_cloud_0","deviceFrame":null,"bevFrameName":null,"id":"8f1f9f25-2f9d-4f6e-9b32-12377386f1b2","type":"SEGMENTATION","classId":433092,"className":"green","classNumber":1,"classValues":[],"createdAt":1713497159000,"createdBy":10088},{"trackId":"6021755c-2c23-4fe5-9de1-699d211eca1e","trackName":"2","contour":{"pointN":4191,"points":[]},"no":2,"deviceName":"lidar_point_cloud_0","deviceFrame":null,"bevFrameName":null,"id":"2623dd98-7e1d-437e-8d2a-91caf4feb279","type":"SEGMENTATION","classId":433091,"className":"red","classNumber":2,"classValues":[],"createdAt":1713497159000,"createdBy":10088},{"trackId":"74726d18-3804-412c-9f2d-49dff6bf515e","trackName":"3","contour":{"pointN":12,"points":[]},"no":3,"deviceName":"lidar_point_cloud_0","deviceFrame":null,"bevFrameName":null,"id":"aa587e52-6463-4a01-b7c6-7bfbc1cc28f7","type":"SEGMENTATION","classId":433093,"className":"blue","classNumber":4,"classValues":[],"createdAt":1713497159000,"createdBy":10088},{"trackId":"2ea5650c-13d2-45e4-baa3-2f802b7ff18f","trackName":"4","contour":{"pointN":1403,"points":[]},"no":4,"deviceName":"lidar_point_cloud_0","deviceFrame":null,"bevFrameName":null,"id":"344d2253-b7a4-4a31-8a45-822be389575e","type":"SEGMENTATION","classId":403778,"className":"pink","classNumber":3,"classValues":[],"createdAt":1715567214000,"createdBy":10524}],"entities":[],"relations":[]}]