[{"version":"1.0","dataId":4917403,"sourceId":104475,"sourceType":"TASK","sourceName":"SHJD-点云分割-20240418-(3)","validity":"UNKNOWN","classifications":[],"instances":[],"segments":[{"trackId":"6354dfea-b27d-4104-9776-c1be2ff6ea55","trackName":"1","contour":{"pointN":30207,"points":[]},"no":1,"deviceName":"lidar_point_cloud_0","deviceFrame":null,"bevFrameName":null,"id":"9d638875-05e3-4606-bc22-efe9c076ee87","type":"SEGMENTATION","classId":433092,"className":"green","classNumber":1,"classValues":[],"createdAt":1713497156000,"createdBy":10088},{"trackId":"598c5f49-3c0c-4ef8-a4e3-fda0657222a0","trackName":"2","contour":{"pointN":3977,"points":[]},"no":2,"deviceName":"lidar_point_cloud_0","deviceFrame":null,"bevFrameName":null,"id":"6d02c45f-d730-4481-9ca8-f0d617667c02","type":"SEGMENTATION","classId":433091,"className":"red","classNumber":2,"classValues":[],"createdAt":1713497156000,"createdBy":10088},{"trackId":"878bafaf-1cc2-4869-b9c7-0967cd7fc6d8","trackName":"5","contour":{"pointN":67,"points":[]},"no":3,"deviceName":"lidar_point_cloud_0","deviceFrame":null,"bevFrameName":null,"id":"fda62520-fee3-4d39-a537-9f098e6d9512","type":"SEGMENTATION","classId":433093,"className":"blue","classNumber":4,"classValues":[],"createdAt":1713921732000,"createdBy":101110},{"trackId":"e4f9c504-520c-4e7d-846c-f1275ca8ad1c","trackName":"6","contour":{"pointN":574,"points":[]},"no":4,"deviceName":"lidar_point_cloud_0","deviceFrame":null,"bevFrameName":null,"id":"808c5f22-7322-4ad0-8ee1-ab19d45c4f92","type":"SEGMENTATION","classId":403778,"className":"pink","classNumber":3,"classValues":[],"createdAt":1715752340000,"createdBy":10524}],"entities":[],"relations":[]}]