[{"version":"1.0","dataId":4917411,"sourceId":104475,"sourceType":"TASK","sourceName":"SHJD-点云分割-20240418-(3)","validity":"UNKNOWN","classifications":[],"instances":[],"segments":[{"trackId":"1396a530-5ced-4cf3-90aa-13055c6e56a5","trackName":"1","contour":{"pointN":29692,"points":[]},"no":1,"deviceName":"lidar_point_cloud_0","deviceFrame":null,"bevFrameName":null,"id":"55163ee5-b501-457e-b688-67f52697cdfe","type":"SEGMENTATION","classId":433092,"className":"green","classNumber":1,"classValues":[],"createdAt":1713497156000,"createdBy":10088},{"trackId":"43b3fc8f-0383-417e-a2bc-ce8b31b730a5","trackName":"2","contour":{"pointN":4194,"points":[]},"no":2,"deviceName":"lidar_point_cloud_0","deviceFrame":null,"bevFrameName":null,"id":"3640a16b-5536-43c7-909c-4584171d8bff","type":"SEGMENTATION","classId":433091,"className":"red","classNumber":2,"classValues":[],"createdAt":1713497156000,"createdBy":10088},{"trackId":"e0601cbd-51e4-4e7d-bb1c-d10c0219c863","trackName":"4","contour":{"pointN":172,"points":[]},"no":3,"deviceName":"lidar_point_cloud_0","deviceFrame":null,"bevFrameName":null,"id":"c2973223-188e-42d1-9270-26fa3f218875","type":"SEGMENTATION","classId":433093,"className":"blue","classNumber":4,"classValues":[],"createdAt":1714031752000,"createdBy":101407},{"trackId":"e1ef3624-81d4-4209-8edb-db8007249e21","trackName":"5","contour":{"pointN":1343,"points":[]},"no":4,"deviceName":"lidar_point_cloud_0","deviceFrame":null,"bevFrameName":null,"id":"33adf8b1-4e4b-42fd-a57b-2ab674b50ae5","type":"SEGMENTATION","classId":403778,"className":"pink","classNumber":3,"classValues":[],"createdAt":1715755913000,"createdBy":10524}],"entities":[],"relations":[]}]