[{"version":"1.0","dataId":4917533,"sourceId":104477,"sourceType":"TASK","sourceName":"SHJD-点云分割-20240418-(5)","validity":"UNKNOWN","classifications":[],"instances":[],"segments":[{"trackId":"dfa5b06f-4eed-495d-bc91-f90a2985ab34","trackName":"4","contour":{"pointN":3971,"points":[]},"no":1,"deviceName":"lidar_point_cloud_0","deviceFrame":null,"bevFrameName":null,"id":"bf11e4b3-4085-4a47-90e9-628b7aa60007","type":"SEGMENTATION","classId":433091,"className":"red","classNumber":2,"classValues":[],"createdAt":1714113280000,"createdBy":100063},{"trackId":"6ee08488-77c1-4ef6-a42a-75bfffef2bfd","trackName":"8","contour":{"pointN":198,"points":[]},"no":2,"deviceName":"lidar_point_cloud_0","deviceFrame":null,"bevFrameName":null,"id":"37f84ea3-4a5c-48fe-afee-cfc5ca69a260","type":"SEGMENTATION","classId":433093,"className":"blue","classNumber":4,"classValues":[],"createdAt":1714115461000,"createdBy":100063},{"trackId":"152a7595-948a-410d-b016-308a2107a71a","trackName":"9","contour":{"pointN":32681,"points":[]},"no":3,"deviceName":"lidar_point_cloud_0","deviceFrame":null,"bevFrameName":null,"id":"63a5ef43-d706-45ba-9754-7030a97c7af1","type":"SEGMENTATION","classId":433092,"className":"green","classNumber":1,"classValues":[],"createdAt":1714116737000,"createdBy":100063},{"trackId":"6d02e862-217e-425a-b4ed-7f6a45d385db","trackName":"10","contour":{"pointN":702,"points":[]},"no":4,"deviceName":"lidar_point_cloud_0","deviceFrame":null,"bevFrameName":null,"id":"88b0c186-449c-4bc2-a89c-d6db6b1eb8fd","type":"SEGMENTATION","classId":403778,"className":"pink","classNumber":3,"classValues":[],"createdAt":1715753979000,"createdBy":100063}],"entities":[],"relations":[]}]