[{"version":"1.0","dataId":4917163,"sourceId":104473,"sourceType":"TASK","sourceName":"SHJD-点云分割-20240418-(1)","validity":"UNKNOWN","classifications":[],"instances":[],"segments":[{"trackId":"c2bddf8a-d00e-4ce1-a3d9-0087fb489bb3","trackName":"1","contour":{"pointN":26725,"points":[]},"no":1,"deviceName":"lidar_point_cloud_0","deviceFrame":null,"bevFrameName":null,"id":"56fb6095-80c6-4b3a-a340-348d00840b40","type":"SEGMENTATION","classId":433092,"className":"green","classNumber":1,"classValues":[],"createdAt":1713497152000,"createdBy":10088},{"trackId":"d9947a1f-42fe-4c52-b628-bef7a524d510","trackName":"2","contour":{"pointN":6483,"points":[]},"no":2,"deviceName":"lidar_point_cloud_0","deviceFrame":null,"bevFrameName":null,"id":"78fc1021-5736-4945-b3fd-5cabd5de969c","type":"SEGMENTATION","classId":433091,"className":"red","classNumber":2,"classValues":[],"createdAt":1713497152000,"createdBy":10088},{"trackId":"b448f031-f5c6-4a89-8d63-8a0b5d9661f7","trackName":"5","contour":{"pointN":506,"points":[]},"no":3,"deviceName":"lidar_point_cloud_0","deviceFrame":null,"bevFrameName":null,"id":"f8df4273-7511-4040-8d81-86d3d9831596","type":"SEGMENTATION","classId":433091,"className":"red","classNumber":2,"classValues":[],"createdAt":1713755769000,"createdBy":370208},{"trackId":"ccba3240-d0f7-4193-889f-41fae7d82524","trackName":"15","contour":{"pointN":255,"points":[]},"no":4,"deviceName":"lidar_point_cloud_0","deviceFrame":null,"bevFrameName":null,"id":"907dc662-6b71-49a6-86dc-e0e57dda179f","type":"SEGMENTATION","classId":403778,"className":"pink","classNumber":3,"classValues":[],"createdAt":1713756090000,"createdBy":370208},{"trackId":"c2c8f202-5a5d-44f7-bdfa-4e07c791f251","trackName":"17","contour":{"pointN":127,"points":[]},"no":5,"deviceName":"lidar_point_cloud_0","deviceFrame":null,"bevFrameName":null,"id":"85527c13-7a5a-4858-b134-db060b525bd9","type":"SEGMENTATION","classId":433091,"className":"red","classNumber":2,"classValues":[],"createdAt":1713756228000,"createdBy":370208},{"trackId":"b2dcde35-2c1f-4584-96c8-8d7f44af4b10","trackName":"21","contour":{"pointN":191,"points":[]},"no":6,"deviceName":"lidar_point_cloud_0","deviceFrame":null,"bevFrameName":null,"id":"45f6e7c9-06cd-4a3e-9e73-c37aa5fb69a2","type":"SEGMENTATION","classId":433091,"className":"red","classNumber":2,"classValues":[],"createdAt":1713757162000,"createdBy":370208},{"trackId":"6865635a-f049-44b3-9554-dffc19dabcbc","trackName":"22","contour":{"pointN":6,"points":[]},"no":7,"deviceName":"lidar_point_cloud_0","deviceFrame":null,"bevFrameName":null,"id":"6eaa05e0-e8f0-4000-9d72-7b96e1d49e41","type":"SEGMENTATION","classId":433091,"className":"red","classNumber":2,"classValues":[],"createdAt":1713757327000,"createdBy":370208},{"trackId":"2949c83c-4dfb-4a89-ae84-bd169d22f6c4","trackName":"28","contour":{"pointN":23,"points":[]},"no":8,"deviceName":"lidar_point_cloud_0","deviceFrame":null,"bevFrameName":null,"id":"accc9fe8-609d-43a3-85f7-90807c9753be","type":"SEGMENTATION","classId":433093,"className":"blue","classNumber":4,"classValues":[],"createdAt":1713931749000,"createdBy":370210},{"trackId":"25af7a07-babb-4a35-9cd1-fa25ca6d1487","trackName":"29","contour":{"pointN":5,"points":[]},"no":9,"deviceName":"lidar_point_cloud_0","deviceFrame":null,"bevFrameName":null,"id":"9735d904-aabd-4ddb-bb97-45731183b848","type":"SEGMENTATION","classId":433093,"className":"blue","classNumber":4,"classValues":[],"createdAt":1713931757000,"createdBy":370210},{"trackId":"c3663722-2948-4c54-8a1e-786e29df60f2","trackName":"30","contour":{"pointN":2834,"points":[]},"no":10,"deviceName":"lidar_point_cloud_0","deviceFrame":null,"bevFrameName":null,"id":"117bd574-adb0-4292-88d8-87a27b2656f1","type":"SEGMENTATION","classId":403778,"className":"pink","classNumber":3,"classValues":[],"createdAt":1713931785000,"createdBy":370210},{"trackId":"eb36763f-95e7-4f84-a9ee-bdc3553e3861","trackName":"31","contour":{"pointN":2,"points":[]},"no":11,"deviceName":"lidar_point_cloud_0","deviceFrame":null,"bevFrameName":null,"id":"c4217fcb-d951-4cae-8b3e-6f484769cea0","type":"SEGMENTATION","classId":403778,"className":"pink","classNumber":3,"classValues":[],"createdAt":1713931835000,"createdBy":370210},{"trackId":"69a66595-5aca-44b8-ad41-c05cba4cf709","trackName":"32","contour":{"pointN":3,"points":[]},"no":12,"deviceName":"lidar_point_cloud_0","deviceFrame":null,"bevFrameName":null,"id":"f0c7a492-6a9b-4626-9879-4047b71a17e4","type":"SEGMENTATION","classId":433093,"className":"blue","classNumber":4,"classValues":[],"createdAt":1713931873000,"createdBy":370210},{"trackId":"c5692b1a-91b5-4ade-94d9-20d0397ebba7","trackName":"33","contour":{"pointN":359,"points":[]},"no":13,"deviceName":"lidar_point_cloud_0","deviceFrame":null,"bevFrameName":null,"id":"a5a3822f-e233-4870-aa3b-cd46d0e46511","type":"SEGMENTATION","classId":433091,"className":"red","classNumber":2,"classValues":[],"createdAt":1713931958000,"createdBy":370210},{"trackId":"dc5c2767-0363-430a-a8ab-6084b9d50172","trackName":"35","contour":{"pointN":27,"points":[]},"no":14,"deviceName":"lidar_point_cloud_0","deviceFrame":null,"bevFrameName":null,"id":"571541a0-bbd2-48c8-996b-6fcebf2d8db9","type":"SEGMENTATION","classId":433091,"className":"red","classNumber":2,"classValues":[],"createdAt":1713931976000,"createdBy":370210},{"trackId":"403c1a11-962e-471e-a6ce-cffd8a84ab90","trackName":"36","contour":{"pointN":7,"points":[]},"no":15,"deviceName":"lidar_point_cloud_0","deviceFrame":null,"bevFrameName":null,"id":"ccd7c039-cee6-4fe6-b029-f81894119fa9","type":"SEGMENTATION","classId":433092,"className":"green","classNumber":1,"classValues":[],"createdAt":1713932005000,"createdBy":370210},{"trackId":"a9e9ed6a-2980-4c8e-92c4-1b711a7432c0","trackName":"37","contour":{"pointN":244,"points":[]},"no":16,"deviceName":"lidar_point_cloud_0","deviceFrame":null,"bevFrameName":null,"id":"acef853b-ea2a-4174-900b-bd6c7878e601","type":"SEGMENTATION","classId":433091,"className":"red","classNumber":2,"classValues":[],"createdAt":1713932016000,"createdBy":370210},{"trackId":"7d2b3bb4-625b-46f3-8e1f-8cba136e4f42","trackName":"38","contour":{"pointN":5,"points":[]},"no":17,"deviceName":"lidar_point_cloud_0","deviceFrame":null,"bevFrameName":null,"id":"a4ce3df6-3132-4ce6-8be1-33078456f8e8","type":"SEGMENTATION","classId":433091,"className":"red","classNumber":2,"classValues":[],"createdAt":1713932031000,"createdBy":370210},{"trackId":"a5ee5f6c-d56b-4d88-958f-6076048ee9a8","trackName":"39","contour":{"pointN":32,"points":[]},"no":18,"deviceName":"lidar_point_cloud_0","deviceFrame":null,"bevFrameName":null,"id":"21c77d72-e06e-4cd6-97aa-06089582c51a","type":"SEGMENTATION","classId":433091,"className":"red","classNumber":2,"classValues":[],"createdAt":1713932086000,"createdBy":370210},{"trackId":"ed75d75a-64d1-4bdf-a500-091c583bc1b6","trackName":"40","contour":{"pointN":13,"points":[]},"no":19,"deviceName":"lidar_point_cloud_0","deviceFrame":null,"bevFrameName":null,"id":"c6bdf16b-e2cb-4edb-b7d3-fdc94dc6298d","type":"SEGMENTATION","classId":433091,"className":"red","classNumber":2,"classValues":[],"createdAt":1713932090000,"createdBy":370210},{"trackId":"004b78bf-fe85-4b09-95f7-d8c2d685a229","trackName":"43","contour":{"pointN":10,"points":[]},"no":20,"deviceName":"lidar_point_cloud_0","deviceFrame":null,"bevFrameName":null,"id":"4f003e59-c426-493f-8132-846afafc4ee9","type":"SEGMENTATION","classId":433091,"className":"red","classNumber":2,"classValues":[],"createdAt":1713932130000,"createdBy":370210},{"trackId":"605fce9c-70d5-48ff-b5ad-68aac4294f88","trackName":"44","contour":{"pointN":10,"points":[]},"no":21,"deviceName":"lidar_point_cloud_0","deviceFrame":null,"bevFrameName":null,"id":"f06ba7f8-7c61-4813-9849-cd638f93a2c0","type":"SEGMENTATION","classId":433091,"className":"red","classNumber":2,"classValues":[],"createdAt":1713932140000,"createdBy":370210},{"trackId":"fd5c99fe-2b4e-4895-beb5-3d650aae5c29","trackName":"45","contour":{"pointN":1,"points":[]},"no":22,"deviceName":"lidar_point_cloud_0","deviceFrame":null,"bevFrameName":null,"id":"049fe816-b005-44cd-b145-248647e6334f","type":"SEGMENTATION","classId":433091,"className":"red","classNumber":2,"classValues":[],"createdAt":1713932153000,"createdBy":370210},{"trackId":"57b15d7e-47af-408f-ac69-291b6e687c2f","trackName":"47","contour":{"pointN":67,"points":[]},"no":23,"deviceName":"lidar_point_cloud_0","deviceFrame":null,"bevFrameName":null,"id":"3409af9d-ef70-41fe-a4db-488b7ebae3f6","type":"SEGMENTATION","classId":433091,"className":"red","classNumber":2,"classValues":[],"createdAt":1713932918000,"createdBy":370210},{"trackId":"6157eec1-4b81-4272-a569-6b97b3b46d6b","trackName":"48","contour":{"pointN":1,"points":[]},"no":24,"deviceName":"lidar_point_cloud_0","deviceFrame":null,"bevFrameName":null,"id":"aee95c97-5766-4416-9606-f1c271a20b71","type":"SEGMENTATION","classId":433091,"className":"red","classNumber":2,"classValues":[],"createdAt":1713932950000,"createdBy":370210},{"trackId":"3c380347-f92e-4b33-bacb-6d864e8f52b8","trackName":"50","contour":{"pointN":49,"points":[]},"no":25,"deviceName":"lidar_point_cloud_0","deviceFrame":null,"bevFrameName":null,"id":"ba390fca-bd5a-4966-b90a-b01a83a9936c","type":"SEGMENTATION","classId":433092,"className":"green","classNumber":1,"classValues":[],"createdAt":1713932996000,"createdBy":370210},{"trackId":"3c161e9b-8fcb-4b59-a795-1e4de1c591c3","trackName":"51","contour":{"pointN":149,"points":[]},"no":26,"deviceName":"lidar_point_cloud_0","deviceFrame":null,"bevFrameName":null,"id":"c17c1fa9-7472-4947-83bf-2f69f1db1860","type":"SEGMENTATION","classId":433091,"className":"red","classNumber":2,"classValues":[],"createdAt":1713933005000,"createdBy":370210},{"trackId":"36e70f66-1c3f-4a5b-8856-2cea70c8f300","trackName":"52","contour":{"pointN":250,"points":[]},"no":27,"deviceName":"lidar_point_cloud_0","deviceFrame":null,"bevFrameName":null,"id":"e8ae9d11-73d0-4715-b308-3f18b5773d76","type":"SEGMENTATION","classId":433091,"className":"red","classNumber":2,"classValues":[],"createdAt":1713933017000,"createdBy":370210},{"trackId":"a54bb3f0-008f-4463-8ac5-3cd52a63ced1","trackName":"53","contour":{"pointN":2,"points":[]},"no":28,"deviceName":"lidar_point_cloud_0","deviceFrame":null,"bevFrameName":null,"id":"751bee0f-ce46-4206-8898-dbdeea329d26","type":"SEGMENTATION","classId":433091,"className":"red","classNumber":2,"classValues":[],"createdAt":1713933030000,"createdBy":370210},{"trackId":"49b0d649-157d-4274-952c-d2d06bfbeb5e","trackName":"54","contour":{"pointN":43,"points":[]},"no":29,"deviceName":"lidar_point_cloud_0","deviceFrame":null,"bevFrameName":null,"id":"f01d38f2-1ff2-4bce-b421-123f2c783064","type":"SEGMENTATION","classId":433091,"className":"red","classNumber":2,"classValues":[],"createdAt":1713933052000,"createdBy":370210},{"trackId":"17a6000d-5cb0-4e7d-a016-8253cbba0c8a","trackName":"55","contour":{"pointN":67,"points":[]},"no":30,"deviceName":"lidar_point_cloud_0","deviceFrame":null,"bevFrameName":null,"id":"f384de62-1688-4eb0-888f-b5c36206a07e","type":"SEGMENTATION","classId":433091,"className":"red","classNumber":2,"classValues":[],"createdAt":1713933071000,"createdBy":370210},{"trackId":"3968d42a-9b61-453d-bc07-4d91387b74fd","trackName":"56","contour":{"pointN":26,"points":[]},"no":31,"deviceName":"lidar_point_cloud_0","deviceFrame":null,"bevFrameName":null,"id":"6a7cea88-a182-4f5d-bfb8-93df4d3004cf","type":"SEGMENTATION","classId":433091,"className":"red","classNumber":2,"classValues":[],"createdAt":1713933100000,"createdBy":370210},{"trackId":"5d52084e-1ee7-4fb9-a2b3-553a2009fb04","trackName":"58","contour":{"pointN":7,"points":[]},"no":32,"deviceName":"lidar_point_cloud_0","deviceFrame":null,"bevFrameName":null,"id":"956fa67b-8012-4212-a808-5a1832fd2307","type":"SEGMENTATION","classId":433091,"className":"red","classNumber":2,"classValues":[],"createdAt":1713933114000,"createdBy":370210},{"trackId":"364896a1-e483-40ca-b0e2-3d644fbfd86a","trackName":"59","contour":{"pointN":1,"points":[]},"no":33,"deviceName":"lidar_point_cloud_0","deviceFrame":null,"bevFrameName":null,"id":"0ffab294-5040-465a-beeb-81c8836a2c87","type":"SEGMENTATION","classId":433091,"className":"red","classNumber":2,"classValues":[],"createdAt":1713933123000,"createdBy":370210},{"trackId":"9edf7c0a-2dd3-49cf-b565-023e8217dc39","trackName":"60","contour":{"pointN":22,"points":[]},"no":34,"deviceName":"lidar_point_cloud_0","deviceFrame":null,"bevFrameName":null,"id":"a9caf4cf-4cd0-474f-a0d5-f1cd0aa3f4e3","type":"SEGMENTATION","classId":433091,"className":"red","classNumber":2,"classValues":[],"createdAt":1713933134000,"createdBy":370210},{"trackId":"56e1350a-1c87-450e-8c63-6dd0291df1e4","trackName":"61","contour":{"pointN":42,"points":[]},"no":35,"deviceName":"lidar_point_cloud_0","deviceFrame":null,"bevFrameName":null,"id":"c4e84359-36a7-428b-b96d-8cffabafbe9e","type":"SEGMENTATION","classId":433091,"className":"red","classNumber":2,"classValues":[],"createdAt":1713933146000,"createdBy":370210},{"trackId":"76687f20-a56a-4a6e-b5c8-b82c6a0a1c04","trackName":"62","contour":{"pointN":5,"points":[]},"no":36,"deviceName":"lidar_point_cloud_0","deviceFrame":null,"bevFrameName":null,"id":"b03c10f8-fa20-43f6-9671-ce86e6273a76","type":"SEGMENTATION","classId":433092,"className":"green","classNumber":1,"classValues":[],"createdAt":1713933160000,"createdBy":370210},{"trackId":"39294bdd-8aba-41fe-8272-09ad2b81a881","trackName":"63","contour":{"pointN":22,"points":[]},"no":37,"deviceName":"lidar_point_cloud_0","deviceFrame":null,"bevFrameName":null,"id":"1020dc19-9d09-44e7-bd12-2138ff21348b","type":"SEGMENTATION","classId":433091,"className":"red","classNumber":2,"classValues":[],"createdAt":1713933167000,"createdBy":370210},{"trackId":"a6af9656-6f06-4736-870d-8e8c5acc95bc","trackName":"64","contour":{"pointN":8,"points":[]},"no":38,"deviceName":"lidar_point_cloud_0","deviceFrame":null,"bevFrameName":null,"id":"2be2ca3d-3342-4254-9ef4-e64730101cda","type":"SEGMENTATION","classId":433092,"className":"green","classNumber":1,"classValues":[],"createdAt":1713933179000,"createdBy":370210},{"trackId":"24172065-ac95-45a5-9533-7253552491a2","trackName":"65","contour":{"pointN":2,"points":[]},"no":39,"deviceName":"lidar_point_cloud_0","deviceFrame":null,"bevFrameName":null,"id":"0c1979cc-dba2-415f-8098-3ea810210700","type":"SEGMENTATION","classId":433092,"className":"green","classNumber":1,"classValues":[],"createdAt":1713933185000,"createdBy":370210},{"trackId":"8004ab53-304c-4897-a0af-341c2cf91828","trackName":"66","contour":{"pointN":232,"points":[]},"no":40,"deviceName":"lidar_point_cloud_0","deviceFrame":null,"bevFrameName":null,"id":"f8a4c676-63ee-4e25-8858-df03d9a90562","type":"SEGMENTATION","classId":433091,"className":"red","classNumber":2,"classValues":[],"createdAt":1713933256000,"createdBy":370210},{"trackId":"e6e77335-05a7-48ef-8cc2-a6ba1f5e2b07","trackName":"67","contour":{"pointN":7,"points":[]},"no":41,"deviceName":"lidar_point_cloud_0","deviceFrame":null,"bevFrameName":null,"id":"0ff73668-e490-49da-aade-450da5a5be6c","type":"SEGMENTATION","classId":403778,"className":"pink","classNumber":3,"classValues":[],"createdAt":1713933334000,"createdBy":370210},{"trackId":"a46afdb3-1b7c-4bd8-b95c-05080efa29ad","trackName":"68","contour":{"pointN":6,"points":[]},"no":42,"deviceName":"lidar_point_cloud_0","deviceFrame":null,"bevFrameName":null,"id":"9096046a-2e75-43c8-a888-65c9c2b7605d","type":"SEGMENTATION","classId":403778,"className":"pink","classNumber":3,"classValues":[],"createdAt":1713933340000,"createdBy":370210},{"trackId":"a63629f0-ce13-488b-9cc9-54ac457923ee","trackName":"70","contour":{"pointN":56,"points":[]},"no":43,"deviceName":"lidar_point_cloud_0","deviceFrame":null,"bevFrameName":null,"id":"6344a0dc-ee9a-4e0b-bc93-27e98045df32","type":"SEGMENTATION","classId":403778,"className":"pink","classNumber":3,"classValues":[],"createdAt":1713933421000,"createdBy":370210},{"trackId":"f1bbdd2d-d296-4ac2-bc51-2041b902ab88","trackName":"71","contour":{"pointN":8,"points":[]},"no":44,"deviceName":"lidar_point_cloud_0","deviceFrame":null,"bevFrameName":null,"id":"7547ccb8-e8b8-4b28-a0ed-45952eef187e","type":"SEGMENTATION","classId":403778,"className":"pink","classNumber":3,"classValues":[],"createdAt":1713933426000,"createdBy":370210},{"trackId":"e3133684-3f16-44ab-a013-c176817dd589","trackName":"72","contour":{"pointN":4,"points":[]},"no":45,"deviceName":"lidar_point_cloud_0","deviceFrame":null,"bevFrameName":null,"id":"451d9670-0930-48be-8f8e-997c8588aab9","type":"SEGMENTATION","classId":403778,"className":"pink","classNumber":3,"classValues":[],"createdAt":1713934153000,"createdBy":370210},{"trackId":"4324485f-af8b-4e13-9d7c-d19315d427bd","trackName":"73","contour":{"pointN":1,"points":[]},"no":46,"deviceName":"lidar_point_cloud_0","deviceFrame":null,"bevFrameName":null,"id":"0a8192d1-d64e-447a-ad75-28614087e76f","type":"SEGMENTATION","classId":433093,"className":"blue","classNumber":4,"classValues":[],"createdAt":1713934176000,"createdBy":370210},{"trackId":"fd1fe0ca-8097-4a5b-93ac-f25bcbde35cd","trackName":"74","contour":{"pointN":47,"points":[]},"no":47,"deviceName":"lidar_point_cloud_0","deviceFrame":null,"bevFrameName":null,"id":"c1b15734-20d9-4da0-ae59-10fb8f6ac676","type":"SEGMENTATION","classId":433093,"className":"blue","classNumber":4,"classValues":[],"createdAt":1713934210000,"createdBy":370210},{"trackId":"7f25ab1c-c8b9-49bc-9afb-ef5895225cfd","trackName":"75","contour":{"pointN":4,"points":[]},"no":48,"deviceName":"lidar_point_cloud_0","deviceFrame":null,"bevFrameName":null,"id":"e4a39664-ea71-4ec3-97fb-741304e8ef97","type":"SEGMENTATION","classId":433093,"className":"blue","classNumber":4,"classValues":[],"createdAt":1713934215000,"createdBy":370210},{"trackId":"c2a3dc2e-f48e-4d2b-843d-58511ec597b5","trackName":"76","contour":{"pointN":12,"points":[]},"no":49,"deviceName":"lidar_point_cloud_0","deviceFrame":null,"bevFrameName":null,"id":"1c80386f-284c-47b3-91f2-691569ed685a","type":"SEGMENTATION","classId":433093,"className":"blue","classNumber":4,"classValues":[],"createdAt":1713934219000,"createdBy":370210},{"trackId":"608b4667-d331-45fe-945c-c1da2ee667b1","trackName":"77","contour":{"pointN":3,"points":[]},"no":50,"deviceName":"lidar_point_cloud_0","deviceFrame":null,"bevFrameName":null,"id":"d3f5cce7-11c7-4c71-a912-ce2d517d9b15","type":"SEGMENTATION","classId":433093,"className":"blue","classNumber":4,"classValues":[],"createdAt":1713934241000,"createdBy":370210},{"trackId":"8a14b3f6-74ad-4db9-9619-585d5bdbd427","trackName":"78","contour":{"pointN":1,"points":[]},"no":51,"deviceName":"lidar_point_cloud_0","deviceFrame":null,"bevFrameName":null,"id":"356d2104-03bb-4bbc-935b-5e2e0152ffa0","type":"SEGMENTATION","classId":433093,"className":"blue","classNumber":4,"classValues":[],"createdAt":1713934261000,"createdBy":370210}],"entities":[],"relations":[]}]