[{"version":"1.0","dataId":4917497,"sourceId":104476,"sourceType":"TASK","sourceName":"SHJD-点云分割-20240418-(4)","validity":"UNKNOWN","classifications":[],"instances":[],"segments":[{"trackId":"f52f3399-b67f-491a-ae85-ca12cf8fad1e","trackName":"1","contour":{"pointN":23369,"points":[]},"no":1,"deviceName":"lidar_point_cloud_0","deviceFrame":null,"bevFrameName":null,"id":"a8bd6e2a-ed65-484a-bf9d-8abb31a62e4d","type":"SEGMENTATION","classId":433092,"className":"green","classNumber":1,"classValues":[],"createdAt":1713497157000,"createdBy":10088},{"trackId":"af9b1594-e10f-40e7-869c-f69db9d6134e","trackName":"2","contour":{"pointN":4756,"points":[]},"no":2,"deviceName":"lidar_point_cloud_0","deviceFrame":null,"bevFrameName":null,"id":"c20572be-d2b4-4f63-8087-c726cd69eedf","type":"SEGMENTATION","classId":433091,"className":"red","classNumber":2,"classValues":[],"createdAt":1713497157000,"createdBy":10088},{"trackId":"abc05ef8-49e5-4c8e-b5dd-066781cd4fa9","trackName":"4","contour":{"pointN":2226,"points":[]},"no":3,"deviceName":"lidar_point_cloud_0","deviceFrame":null,"bevFrameName":null,"id":"247d8940-5be2-46d5-a92f-e3bf9e21d37f","type":"SEGMENTATION","classId":403778,"className":"pink","classNumber":3,"classValues":[],"createdAt":1715742253000,"createdBy":100217}],"entities":[],"relations":[]}]