[{"version":"1.0","dataId":4917468,"sourceId":104476,"sourceType":"TASK","sourceName":"SHJD-点云分割-20240418-(4)","validity":"UNKNOWN","classifications":[],"instances":[],"segments":[{"trackId":"a20962bb-be05-466a-a65f-9d6e0d842059","trackName":"1","contour":{"pointN":28610,"points":[]},"no":1,"deviceName":"lidar_point_cloud_0","deviceFrame":null,"bevFrameName":null,"id":"43f61d79-1710-4095-83ab-739fafa2a265","type":"SEGMENTATION","classId":433092,"className":"green","classNumber":1,"classValues":[],"createdAt":1713497157000,"createdBy":10088},{"trackId":"f36a9e82-79ad-4f6e-9957-a58442ed8064","trackName":"2","contour":{"pointN":4991,"points":[]},"no":2,"deviceName":"lidar_point_cloud_0","deviceFrame":null,"bevFrameName":null,"id":"7c8941f1-9625-4390-9345-00cb7411eed5","type":"SEGMENTATION","classId":433091,"className":"red","classNumber":2,"classValues":[],"createdAt":1713497157000,"createdBy":10088},{"trackId":"a013cc39-c33d-4b43-b2b3-3f8e1c02c271","trackName":"3","contour":{"pointN":126,"points":[]},"no":3,"deviceName":"lidar_point_cloud_0","deviceFrame":null,"bevFrameName":null,"id":"5a476833-7db1-4c2d-9938-1ca6ec530b1e","type":"SEGMENTATION","classId":433092,"className":"green","classNumber":1,"classValues":[],"createdAt":1713497157000,"createdBy":10088},{"trackId":"ddcf7465-a0fe-423b-bbd0-c604fc493da1","trackName":"4","contour":{"pointN":23,"points":[]},"no":4,"deviceName":"lidar_point_cloud_0","deviceFrame":null,"bevFrameName":null,"id":"2841962e-85c6-4438-a04e-cccb887040c5","type":"SEGMENTATION","classId":433093,"className":"blue","classNumber":4,"classValues":[],"createdAt":1714288416000,"createdBy":10524},{"trackId":"4dae92b3-0239-4146-be69-b676f6b34851","trackName":"5","contour":{"pointN":213,"points":[]},"no":5,"deviceName":"lidar_point_cloud_0","deviceFrame":null,"bevFrameName":null,"id":"fa81eb3e-28ef-4ad8-8ed6-401bebb6b9e3","type":"SEGMENTATION","classId":403778,"className":"pink","classNumber":3,"classValues":[],"createdAt":1715568197000,"createdBy":10524}],"entities":[],"relations":[]}]