[{"version":"1.0","dataId":4917476,"sourceId":104476,"sourceType":"TASK","sourceName":"SHJD-点云分割-20240418-(4)","validity":"UNKNOWN","classifications":[],"instances":[],"segments":[{"trackId":"9fd714d6-1f18-4489-b140-60adba5c0d59","trackName":"1","contour":{"pointN":27535,"points":[]},"no":1,"deviceName":"lidar_point_cloud_0","deviceFrame":null,"bevFrameName":null,"id":"5c00317e-03f7-40dc-90df-e96598e1fce2","type":"SEGMENTATION","classId":433092,"className":"green","classNumber":1,"classValues":[],"createdAt":1713497157000,"createdBy":10088},{"trackId":"45039c8b-448d-493b-95de-ed815f00874d","trackName":"2","contour":{"pointN":4776,"points":[]},"no":2,"deviceName":"lidar_point_cloud_0","deviceFrame":null,"bevFrameName":null,"id":"14f82a33-ccaf-49e6-987b-e00b5b31764b","type":"SEGMENTATION","classId":433091,"className":"red","classNumber":2,"classValues":[],"createdAt":1713497157000,"createdBy":10088},{"trackId":"de5c3351-9236-4566-b911-414e00f26353","trackName":"4","contour":{"pointN":1,"points":[]},"no":3,"deviceName":"lidar_point_cloud_0","deviceFrame":null,"bevFrameName":null,"id":"0914101b-96ca-4e24-86a2-34b72c76b6d3","type":"SEGMENTATION","classId":403778,"className":"pink","classNumber":3,"classValues":[],"createdAt":1715740799000,"createdBy":100217}],"entities":[],"relations":[]}]