[{"version":"1.0","dataId":4917457,"sourceId":104476,"sourceType":"TASK","sourceName":"SHJD-点云分割-20240418-(4)","validity":"UNKNOWN","classifications":[],"instances":[],"segments":[{"trackId":"26578c81-0d17-40ee-818d-6dbc99d54efa","trackName":"1","contour":{"pointN":28777,"points":[]},"no":1,"deviceName":"lidar_point_cloud_0","deviceFrame":null,"bevFrameName":null,"id":"88ec00d1-a8c5-46ac-b694-48ecb037d8bb","type":"SEGMENTATION","classId":433092,"className":"green","classNumber":1,"classValues":[],"createdAt":1713497157000,"createdBy":10088},{"trackId":"df8f7ba8-16f4-4aac-a5a3-02aa55c0b990","trackName":"2","contour":{"pointN":5048,"points":[]},"no":2,"deviceName":"lidar_point_cloud_0","deviceFrame":null,"bevFrameName":null,"id":"29dc48b9-5d7c-45bf-9f08-58a1aecedf15","type":"SEGMENTATION","classId":433091,"className":"red","classNumber":2,"classValues":[],"createdAt":1713497157000,"createdBy":10088},{"trackId":"cec59bdf-483f-4f07-aa45-0f1dade2788b","trackName":"3","contour":{"pointN":7,"points":[]},"no":3,"deviceName":"lidar_point_cloud_0","deviceFrame":null,"bevFrameName":null,"id":"77c03eff-8349-4ab4-9f06-322baec1f094","type":"SEGMENTATION","classId":433093,"className":"blue","classNumber":4,"classValues":[],"createdAt":1713497157000,"createdBy":10088},{"trackId":"799704be-93ca-4c9f-bb55-31dec19cdf31","trackName":"4","contour":{"pointN":15,"points":[]},"no":4,"deviceName":"lidar_point_cloud_0","deviceFrame":null,"bevFrameName":null,"id":"b71acd2c-f01a-4214-931e-ec1eaaab299f","type":"SEGMENTATION","classId":433093,"className":"blue","classNumber":4,"classValues":[],"createdAt":1714271129000,"createdBy":10524},{"trackId":"d4c98b3c-4cdd-4f06-9da5-b4d9bb5344ed","trackName":"5","contour":{"pointN":2982,"points":[]},"no":5,"deviceName":"lidar_point_cloud_0","deviceFrame":null,"bevFrameName":null,"id":"d5be94bc-da22-429e-a566-91afb0a1dc4e","type":"SEGMENTATION","classId":403778,"className":"pink","classNumber":3,"classValues":[],"createdAt":1715568131000,"createdBy":10524}],"entities":[],"relations":[]}]